pairwise_alignments_to_msa/__init__.py
pairwise_alignments_to_msa/alignment.py
pairwise_alignments_to_msa-0.1.1.dist-info/LICENSE
pairwise_alignments_to_msa-0.1.1.dist-info/METADATA
pairwise_alignments_to_msa-0.1.1.dist-info/WHEEL
pairwise_alignments_to_msa-0.1.1.dist-info/RECORD
