Metadata-Version: 2.3
Name: pairwise_alignments_to_msa
Version: 0.1.1
Summary: A tool to convert tuple sequence alignments to multi-sequence alignments.
License: Copyright <2025> <CASSIA BASTRESS>
Keywords: bioinformatics,sequence alignment,msa,tuple alignment
Author: Cassia Bastress
Author-email: cassie.bastress@gmail.com
Requires-Python: >=3.9
Classifier: Development Status :: 3 - Alpha
Classifier: Intended Audience :: Science/Research
Classifier: Intended Audience :: Developers
Classifier: Topic :: Scientific/Engineering :: Bio-Informatics
Classifier: License :: OSI Approved :: MIT License
Classifier: Programming Language :: Python :: 3
Classifier: Programming Language :: Python :: 3.11
Project-URL: Documentation, https://github.com/Cassiebastress/tuplealign#readme
Project-URL: Homepage, https://github.com/Cassiebastress/tuplealign
Project-URL: Issue Tracker, https://github.com/Cassiebastress/tuplealign/issues
Project-URL: Repository, https://github.com/Cassiebastress/tuplealign
